polyomino/.gitignore
polyomino/__init__.py
polyomino/board.py
polyomino/constant.py
polyomino/error.py
polyomino/jupyter.py
polyomino/order.py
polyomino/piece.py
polyomino/problem.py
polyomino/solution.py
polyomino/tileset.py
polyomino/transform.py
polyomino/utils.py
polyomino-0.7.1.dist-info/METADATA
polyomino-0.7.1.dist-info/WHEEL
polyomino-0.7.1.dist-info/entry_points.txt
polyomino-0.7.1.dist-info/RECORD
