Metadata-Version: 2.1
Name: polyomino
Version: 0.7.1
Summary: Solve polyomino tiling problems.
License: MIT
Author: Jack Grahl
Author-email: jack.grahl@gmail.com
Requires-Python: >=3.7.1,<4.0.0
Classifier: License :: OSI Approved :: MIT License
Classifier: Programming Language :: Python :: 3
Classifier: Programming Language :: Python :: 3.8
Classifier: Programming Language :: Python :: 3.9
Classifier: Programming Language :: Python :: 3.10
Classifier: Programming Language :: Python :: 3.11
Requires-Dist: exact-cover (==1.3.0)
Requires-Dist: pretty-poly (==0.5.1)
